salesforce_requests_oauthlib/__init__.py
salesforce_requests_oauthlib-0.1.12.dist-info/AUTHORS
salesforce_requests_oauthlib-0.1.12.dist-info/LICENSE
salesforce_requests_oauthlib-0.1.12.dist-info/METADATA
salesforce_requests_oauthlib-0.1.12.dist-info/WHEEL
salesforce_requests_oauthlib-0.1.12.dist-info/top_level.txt
salesforce_requests_oauthlib-0.1.12.dist-info/RECORD
