Metadata-Version: 2.1
Name: salesforce-requests-oauthlib
Version: 0.1.12
Summary: An extension to requests-oauthlib to use with Salesforce.
Home-page: https://github.com/SalesforceFoundation/salesforce-requests-oauthlib
Author: Adam J. Lincoln
Author-email: alincoln@salesforce.com
License: BSD 3-Clause
Download-URL: https://github.com/SalesforceFoundation/salesforce-requests-oauthlib/tarball/0.1.12
Keywords: salesforce sfdc oauth oauth2
Platform: UNKNOWN
Requires-Dist: requests-oauthlib (>=1.2.0)
Requires-Dist: six
Requires-Dist: psycopg2-binary
